ariadne/__init__.py
ariadne/__main__.py
ariadne/_version.py
ariadne/benchmarking.py
ariadne/benchmarks.py
ariadne/calibration.py
ariadne/converters.py
ariadne/cross_platform_comparison.py
ariadne/datasets.py
ariadne/education.py
ariadne/education_integration.py
ariadne/enhanced_benchmarking.py
ariadne/network_coordination.py
ariadne/quantum_advantage.py
ariadne/regression_detection.py
ariadne/reproducibility.py
ariadne/router.py
ariadne/simulation.py
ariadne/types.py
ariadne/validation.py
ariadne/visualization.py
ariadne/algorithms/__init__.py
ariadne/algorithms/base.py
ariadne/algorithms/error_correction.py
ariadne/algorithms/foundational.py
ariadne/algorithms/machine_learning.py
ariadne/algorithms/optimization.py
ariadne/algorithms/search.py
ariadne/algorithms/specialized.py
ariadne/analysis/competitive_analysis.py
ariadne/async_/__init__.py
ariadne/async_/simulation.py
ariadne/backends/__init__.py
ariadne/backends/azure_backend.py
ariadne/backends/braket_backend.py
ariadne/backends/cirq_backend.py
ariadne/backends/cpu_backend.py
ariadne/backends/cuda_backend.py
ariadne/backends/cuda_kernels.py
ariadne/backends/ddsim_backend.py
ariadne/backends/enhanced_interface.py
ariadne/backends/fallback.py
ariadne/backends/health_checker.py
ariadne/backends/intel_qs_backend.py
ariadne/backends/metal_backend.py
ariadne/backends/metal_shaders.py
ariadne/backends/mps_backend.py
ariadne/backends/pennylane_backend.py
ariadne/backends/performance_monitor.py
ariadne/backends/pool.py
ariadne/backends/qulacs_backend.py
ariadne/backends/tensor_network_backend.py
ariadne/backends/universal_interface.py
ariadne/backends/experimental/__init__.py
ariadne/benchmarks/comprehensive_suite.py
ariadne/cli/__init__.py
ariadne/cli/install.py
ariadne/cli/main.py
ariadne/config/__init__.py
ariadne/config/config.py
ariadne/config/loader.py
ariadne/config/validation.py
ariadne/core/__init__.py
ariadne/core/cache.py
ariadne/core/error_handling.py
ariadne/core/logging.py
ariadne_router-0.4.5.dist-info/licenses/LICENSE
ariadne_router-0.4.5.dist-info/METADATA
ariadne_router-0.4.5.dist-info/WHEEL
ariadne_router-0.4.5.dist-info/entry_points.txt
ariadne_router-0.4.5.dist-info/top_level.txt
ariadne_router-0.4.5.dist-info/RECORD
