Metadata-Version: 2.4
Name: ariadne-router
Version: 0.4.5
Summary: Intelligent quantum simulator router with automatic backend selection
Author-email: Hunter Bown <hunter@shannonlabs.dev>
License: Apache-2.0
Project-URL: Homepage, https://github.com/Hmbown/ariadne
Project-URL: Documentation, https://github.com/Hmbown/ariadne#readme
Project-URL: Source, https://github.com/Hmbown/ariadne
Project-URL: Issues, https://github.com/Hmbown/ariadne/issues
Requires-Python: <3.14,>=3.11
License-File: LICENSE
Provides-Extra: cuda
Requires-Dist: cupy-cuda12x>=12.0.0; extra == "cuda"
Provides-Extra: apple
Requires-Dist: jax>=0.4; (platform_system == "Darwin" and platform_machine == "arm64") and extra == "apple"
Requires-Dist: jaxlib>=0.4; (platform_system == "Darwin" and platform_machine == "arm64") and extra == "apple"
Requires-Dist: jax-metal>=0.1; (platform_system == "Darwin" and platform_machine == "arm64") and extra == "apple"
Provides-Extra: quantum-platforms
Requires-Dist: pennylane>=0.30.0; extra == "quantum-platforms"
Requires-Dist: pyquil>=3.0.0; extra == "quantum-platforms"
Requires-Dist: amazon-braket-sdk>=1.40.0; extra == "quantum-platforms"
Requires-Dist: qsharp>=1.0.0; platform_python_implementation != "PyPy" and extra == "quantum-platforms"
Requires-Dist: pyopencl>=2023.1.0; extra == "quantum-platforms"
Provides-Extra: advanced
Requires-Dist: mqt.ddsim>=2.0.0; extra == "advanced"
Requires-Dist: qulacs>=0.6.4; extra == "advanced"
Requires-Dist: cirq>=1.0.0; extra == "advanced"
Provides-Extra: viz
Requires-Dist: matplotlib>=3.5; extra == "viz"
Requires-Dist: seaborn>=0.11; extra == "viz"
Requires-Dist: plotly>=5.0; extra == "viz"
Provides-Extra: dev
Requires-Dist: pytest>=7.0; extra == "dev"
Requires-Dist: pytest-cov>=3.0; extra == "dev"
Requires-Dist: pytest-asyncio>=0.21.0; extra == "dev"
Requires-Dist: ruff>=0.6.0; extra == "dev"
Requires-Dist: pre-commit>=3.5; extra == "dev"
Requires-Dist: mypy>=1.11.0; extra == "dev"
Requires-Dist: pytest-timeout>=2.1; extra == "dev"
Requires-Dist: pytest-xdist>=2.5; extra == "dev"
Requires-Dist: pytest-mock>=3.6; extra == "dev"
Requires-Dist: coverage>=6.0; extra == "dev"
Requires-Dist: bandit>=1.7; extra == "dev"
Requires-Dist: safety>=2.0; extra == "dev"
Requires-Dist: ipython>=9.0; extra == "dev"
Requires-Dist: pandas>=2.0; extra == "dev"
Requires-Dist: seaborn>=0.13; extra == "dev"
Provides-Extra: docs
Requires-Dist: sphinx>=5.0; extra == "docs"
Requires-Dist: sphinx-rtd-theme>=1.2; extra == "docs"
Requires-Dist: myst-parser>=0.18; extra == "docs"
Dynamic: license-file
